SpaMV/__init__.py
SpaMV/_constraints.py
SpaMV/dist.py
SpaMV/layers.py
SpaMV/metrics.py
SpaMV/model.py
SpaMV/sim.py
SpaMV/spamv.py
SpaMV/utils.py
spamv-1.0.28.dist-info/METADATA
spamv-1.0.28.dist-info/WHEEL
spamv-1.0.28.dist-info/top_level.txt
spamv-1.0.28.dist-info/RECORD
