Metadata-Version: 2.4
Name: SpaMV
Version: 1.0.28
Summary: The Python package for a spatial multi-omics integration algorithm called SpaMV.
Author-email: Yang Liu <yangliu1214@hkbu.edu.hk>
License-Expression: MIT
Project-URL: Homepage, https://github.com/enderlogic/SpaMV
Project-URL: Issues, https://github.com/enderlogic/SpaMV/issues
Classifier: Programming Language :: Python :: 3
Classifier: Operating System :: OS Independent
Requires-Python: >=3.10
Requires-Dist: pyro-ppl
Requires-Dist: scanpy
Requires-Dist: torch_geometric
Requires-Dist: squidpy==1.6.5
Requires-Dist: dask[dataframe]==2024.11.2
Requires-Dist: numpy<2.3
Requires-Dist: rpy2
Requires-Dist: scikit-misc
